catalog_agent/__init__.py
catalog_agent/agent/__init__.py
catalog_agent/agent/catalog_agent.py
catalog_agent/agent/supabase_client.py
catalog_agent/agent/tools.py
catalog_agent/config/DiscoverProducts.json
catalog_agent/config/__init__.py
catalog_agent/config/actions.yaml
catalog_agent/config/config_loader.py
catalog_agent/config/instructions.yaml
catalog_agent/config/intent-synonyms.json
catalog_agent/config/tool-playbook.md
catalog_agent/intent/__init__.py
catalog_agent/intent/intent_service.py
catalog_agent/types/__init__.py
catalog_agent/types/agent.py
catalog_agent/types/core.py
catalog_agent-0.1.6.dist-info/licenses/LICENSE
catalog_agent-0.1.6.dist-info/METADATA
catalog_agent-0.1.6.dist-info/WHEEL
catalog_agent-0.1.6.dist-info/top_level.txt
catalog_agent-0.1.6.dist-info/RECORD
