Metadata-Version: 2.4
Name: catalog-agent
Version: 0.1.6
Summary: AI-powered catalog agent for product discovery and recommendations
Author-email: Your Name <your.email@example.com>
License-Expression: MIT
Project-URL: Homepage, https://github.com/komatadi/catalog-agent
Project-URL: Repository, https://github.com/komatadi/catalog-agent
Classifier: Development Status :: 3 - Alpha
Classifier: Intended Audience :: Developers
Classifier: Programming Language :: Python :: 3.10
Classifier: Programming Language :: Python :: 3.11
Classifier: Programming Language :: Python :: 3.12
Requires-Python: >=3.10
License-File: LICENSE
Requires-Dist: langchain==0.3.7
Requires-Dist: langchain-openai==0.2.8
Requires-Dist: langchain-community==0.3.5
Requires-Dist: pydantic<3.0.0,>=2.9.2
Requires-Dist: pydantic-settings<3.0.0,>=2.6.1
Requires-Dist: supabase==2.9.1
Requires-Dist: python-dotenv==1.0.1
Requires-Dist: pyyaml==6.0.2
Requires-Dist: requests==2.32.3
Provides-Extra: dev
Requires-Dist: pytest==8.3.3; extra == "dev"
Requires-Dist: pytest-asyncio==0.24.0; extra == "dev"
Requires-Dist: black==24.10.0; extra == "dev"
Requires-Dist: ruff==0.7.3; extra == "dev"
Requires-Dist: mypy==1.13.0; extra == "dev"
Dynamic: license-file
